[{"playerName":"Marcus Stoinis","myTeamName":"Delhi Capitals ","opponent Team":"Mumbai Indians ","runs":"0","ball":"1","fours":"0","sixes":"0","sr":"0.00"},{"playerName":"Marcus Stoinis","myTeamName":"Delhi Capitals ","opponent Team":"Mumbai Indians ","runs":"2","ball":"3","fours":"0","sixes":"0","sr":"66.66"},{"playerName":"Marcus Stoinis","myTeamName":"Delhi Capitals ","opponent Team":"Delhi Capitals ","runs":"10","ball":"5","fours":"0","sixes":"1","sr":"200.00"},{"playerName":"Marcus Stoinis","myTeamName":"Delhi Capitals ","opponent Team":"Sunrisers Hyderabad ","runs":"38","ball":"27","fours":"5","sixes":"1","sr":"140.74"},{"playerName":"Marcus Stoinis","myTeamName":"Delhi Capitals ","opponent Team":"Mumbai Indians ","runs":"13","ball":"8","fours":"2","sixes":"0","sr":"162.50"},{"playerName":"Marcus Stoinis","myTeamName":"Delhi Capitals ","opponent Team":"Kings XI Punjab ","runs":"9","ball":"10","fours":"0","sixes":"0","sr":"90.00"},{"playerName":"Marcus Stoinis","myTeamName":"Delhi Capitals ","opponent Team":"Delhi Capitals ","runs":"5","ball":"6","fours":"1","sixes":"0","sr":"83.33"},{"playerName":"Marcus Stoinis","myTeamName":"Delhi Capitals ","opponent Team":"Royal Challengers Bangalore ","runs":"53","ball":"26","fours":"6","sixes":"2","sr":"203.84"},{"playerName":"Marcus Stoinis","myTeamName":"Delhi Capitals ","opponent Team":"Rajasthan Royals ","runs":"39","ball":"30","fours":"0","sixes":"4","sr":"130.00"},{"playerName":"Marcus Stoinis","myTeamName":"Delhi Capitals ","opponent Team":"Delhi Capitals ","runs":"6","ball":"6","fours":"0","sixes":"0","sr":"100.00"},{"playerName":"Marcus Stoinis","myTeamName":"Delhi Capitals ","opponent Team":"Rajasthan Royals ","runs":"18","ball":"19","fours":"1","sixes":"0","sr":"94.73"},{"playerName":"Marcus Stoinis","myTeamName":"Delhi Capitals ","opponent Team":"Chennai Super Kings ","runs":"5","ball":"3","fours":"1","sixes":"0","sr":"166.66"},{"playerName":"Marcus Stoinis","myTeamName":"Delhi Capitals ","opponent Team":"Kings XI Punjab ","runs":"53","ball":"21","fours":"7","sixes":"3","sr":"252.38"},{"playerName":"Marcus Stoinis","myTeamName":"Delhi Capitals ","opponent Team":"Kolkata Knight Riders ","runs":"1","ball":"3","fours":"0","sixes":"0","sr":"33.33"},{"playerName":"Marcus Stoinis","myTeamName":"Delhi Capitals ","opponent Team":"Delhi Capitals ","runs":"24","ball":"14","fours":"1","sixes":"2","sr":"171.42"},{"playerName":"Marcus Stoinis","myTeamName":"Delhi Capitals ","opponent Team":"Delhi Capitals ","runs":"11","ball":"9","fours":"1","sixes":"0","sr":"122.22"},{"playerName":"Marcus Stoinis","myTeamName":"Delhi Capitals ","opponent Team":"Delhi Capitals ","runs":"65","ball":"46","fours":"6","sixes":"3","sr":"141.30"}]